{
  "sites": [
    {
      "id": "ee4744ee-13d8-4d20-8ce7-32e490ee04c8",
      "key": "光速HTTP",
      "name": "光速HTTP",
      "api": "http://api.guangsuapi.com/api.php/provide/vod",
      "type": 2,
      "isActive": 1,
      "time": "2026-07-23T08:35:15.556Z",
      "isDefault": 0,
      "remark": "speed:38ms",
      "tags": [],
      "priority": 0,
      "proxyMode": "none",
      "customProxy": ""
    },
    {
      "id": "19b39687-a93a-4cc5-8a24-58c2875a0e7a",
      "key": "金鹰点播",
      "name": "金鹰点播",
      "api": "https://jinyingzy.com/api.php/provide/vod",
      "type": 2,
      "isActive": 1,
      "time": "2026-07-23T08:35:15.556Z",
      "isDefault": 0,
      "remark": "speed:51ms",
      "tags": [],
      "priority": 0,
      "proxyMode": "none",
      "customProxy": ""
    },
    {
      "id": "e6f7cd69-0ff3-4fb6-9dac-0f04f64cbe99",
      "key": "155",
      "name": "155",
      "api": "https://155api.com/api.php/provide/vod",
      "type": 2,
      "isActive": 1,
      "time": "2026-07-23T08:35:15.556Z",
      "isDefault": 0,
      "remark": "speed:59ms",
      "tags": [],
      "priority": 0,
      "proxyMode": "none",
      "customProxy": ""
    },
    {
      "id": "b46196c9-3cd5-4181-855a-deb0a16e9023",
      "key": "步步高资源",
      "name": "步步高资源",
      "api": "https://api.yparse.com/api/json",
      "type": 2,
      "isActive": 1,
      "time": "2026-07-23T08:35:15.556Z",
      "isDefault": 0,
      "remark": "speed:62ms",
      "tags": [],
      "priority": 0,
      "proxyMode": "none",
      "customProxy": ""
    },
    {
      "id": "2009335e-dc30-4cfb-aae7-7f45b9eed600",
      "key": "百度云资源",
      "name": "百度云资源",
      "api": "https://api.apibdzy.com/api.php/provide/vod",
      "type": 2,
      "isActive": 1,
      "time": "2026-07-23T08:35:15.556Z",
      "isDefault": 0,
      "remark": "speed:104ms",
      "tags": [],
      "priority": 0,
      "proxyMode": "none",
      "customProxy": ""
    },
    {
      "id": "f17a356e-6d1a-4cde-bb53-35cf155fb819",
      "key": "U酷资源88",
      "name": "U酷资源88",
      "api": "https://api.ukuapi88.com/api.php/provide/vod",
      "type": 2,
      "isActive": 1,
      "time": "2026-07-23T08:35:15.556Z",
      "isDefault": 0,
      "remark": "speed:104ms",
      "tags": [],
      "priority": 0,
      "proxyMode": "none",
      "customProxy": ""
    },
    {
      "id": "0be14375-6698-4c1f-a16a-4ac3401101ce",
      "key": "爱蛋资源",
      "name": "爱蛋资源",
      "api": "https://lovedan.net/api.php/provide/vod",
      "type": 2,
      "isActive": 1,
      "time": "2026-07-23T08:35:15.556Z",
      "isDefault": 0,
      "remark": "speed:105ms",
      "tags": [],
      "priority": 0,
      "proxyMode": "none",
      "customProxy": ""
    },
    {
      "id": "0cda5eca-066d-43f8-b2e6-3d6a48e2db97",
      "key": "🫧韩剧┃蓝光",
      "name": "🫧韩剧┃蓝光",
      "api": "https://16409.kstore.vip/js/hanjukan.json",
      "type": 2,
      "isActive": 1,
      "time": "2026-07-23T08:35:15.556Z",
      "isDefault": 0,
      "remark": "speed:107ms",
      "tags": [],
      "priority": 0,
      "proxyMode": "none",
      "customProxy": ""
    },
    {
      "id": "4193d779-dea4-46fb-8cc0-77dada80e375",
      "key": "jkun",
      "name": "jkun",
      "api": "https://jkunzyapi.com/api.php/provide/vod",
      "type": 2,
      "isActive": 1,
      "time": "2026-07-23T08:35:15.556Z",
      "isDefault": 0,
      "remark": "speed:110ms",
      "tags": [],
      "priority": 0,
      "proxyMode": "none",
      "customProxy": ""
    },
    {
      "id": "ef3bef76-9d3e-4d67-87ce-ba4581d164b3",
      "key": "飘零资源",
      "name": "飘零资源",
      "api": "https://p2100.net/api.php/provide/vod",
      "type": 2,
      "isActive": 1,
      "time": "2026-07-23T08:35:15.556Z",
      "isDefault": 0,
      "remark": "speed:112ms",
      "tags": [],
      "priority": 0,
      "proxyMode": "none",
      "customProxy": ""
    },
    {
      "id": "7fbe2662-7760-4629-add3-77a147a9268f",
      "key": "🥅企鹅┃体育直播",
      "name": "🥅企鹅┃体育直播",
      "api": "https://16409.kstore.vip/js/%E4%BC%81%E9%B9%85%E7%9B%B4%E6%92%AD.json",
      "type": 2,
      "isActive": 1,
      "time": "2026-07-23T08:35:15.556Z",
      "isDefault": 0,
      "remark": "speed:114ms",
      "tags": [],
      "priority": 0,
      "proxyMode": "none",
      "customProxy": ""
    },
    {
      "id": "352d02e5-cb7c-448c-b592-b617255ba5af",
      "key": "🎧全网┃音乐",
      "name": "🎧全网┃音乐",
      "api": "https://16409.kstore.vip/js/%E5%93%94%E5%93%A9MTV.json",
      "type": 2,
      "isActive": 1,
      "time": "2026-07-23T08:35:15.556Z",
      "isDefault": 0,
      "remark": "speed:115ms",
      "tags": [],
      "priority": 0,
      "proxyMode": "none",
      "customProxy": ""
    },
    {
      "id": "861cb936-c95f-4208-84a6-5800229448ac",
      "key": "索尼资源",
      "name": "索尼资源",
      "api": "https://suoniapi.com/api.php/provide/vod",
      "type": 2,
      "isActive": 1,
      "time": "2026-07-23T08:35:15.556Z",
      "isDefault": 0,
      "remark": "speed:116ms",
      "tags": [],
      "priority": 0,
      "proxyMode": "none",
      "customProxy": ""
    },
    {
      "id": "db230245-916e-4bca-9947-38cf699230f3",
      "key": "最大资源",
      "name": "最大资源",
      "api": "https://api.zuidapi.com/api.php/provide/vod",
      "type": 2,
      "isActive": 1,
      "time": "2026-07-23T08:35:15.556Z",
      "isDefault": 0,
      "remark": "speed:118ms",
      "tags": [],
      "priority": 0,
      "proxyMode": "none",
      "customProxy": ""
    },
    {
      "id": "5df16c9e-6f91-48cd-a7e1-6efe885a0c6b",
      "key": "CK",
      "name": "CK",
      "api": "https://www.ckzy1.com/api.php/provide/vod",
      "type": 2,
      "isActive": 1,
      "time": "2026-07-23T08:35:15.556Z",
      "isDefault": 0,
      "remark": "speed:124ms",
      "tags": [],
      "priority": 0,
      "proxyMode": "none",
      "customProxy": ""
    },
    {
      "id": "8146d783-d1f6-43ed-a201-d2078dc05b6b",
      "key": "乐子HTTP",
      "name": "乐子HTTP",
      "api": "http://cj.lziapi.com/api.php/provide/vod",
      "type": 2,
      "isActive": 1,
      "time": "2026-07-23T08:35:15.556Z",
      "isDefault": 0,
      "remark": "speed:137ms",
      "tags": [],
      "priority": 0,
      "proxyMode": "none",
      "customProxy": ""
    },
    {
      "id": "3c31af97-7f2e-4d2c-b77c-c51663a78f47",
      "key": "小鸡资源",
      "name": "小鸡资源",
      "api": "https://api.xiaojizy.live/provide/vod",
      "type": 2,
      "isActive": 1,
      "time": "2026-07-23T08:35:15.556Z",
      "isDefault": 0,
      "remark": "speed:145ms",
      "tags": [],
      "priority": 0,
      "proxyMode": "none",
      "customProxy": ""
    },
    {
      "id": "65c203f5-46de-4897-9dce-9a259144386a",
      "key": "丫丫点播",
      "name": "丫丫点播",
      "api": "https://cj.yayazy.net/api.php/provide/vod",
      "type": 2,
      "isActive": 1,
      "time": "2026-07-23T08:35:15.556Z",
      "isDefault": 0,
      "remark": "speed:154ms",
      "tags": [],
      "priority": 0,
      "proxyMode": "none",
      "customProxy": ""
    },
    {
      "id": "c1d05b1e-c780-4f60-8883-1fc9e08afd0f",
      "key": "暴风APP",
      "name": "暴风APP",
      "api": "https://app.bfzyapi.com/api.php/provide/vod",
      "type": 2,
      "isActive": 1,
      "time": "2026-07-23T08:35:15.556Z",
      "isDefault": 0,
      "remark": "speed:165ms",
      "tags": [],
      "priority": 0,
      "proxyMode": "none",
      "customProxy": ""
    },
    {
      "id": "6e0fd64f-78a0-4ade-98ea-831a2a20efce",
      "key": "新浪HTTPS",
      "name": "新浪HTTPS",
      "api": "https://api.xinlangapi.com/xinlangapi.php/provide/vod",
      "type": 2,
      "isActive": 1,
      "time": "2026-07-23T08:35:15.556Z",
      "isDefault": 0,
      "remark": "speed:170ms",
      "tags": [],
      "priority": 0,
      "proxyMode": "none",
      "customProxy": ""
    },
    {
      "id": "d3b67c12-f5ea-46a8-8bcd-d3628a131b99",
      "key": "无尽NET",
      "name": "无尽NET",
      "api": "https://api.wujinapi.net/api.php/provide/vod",
      "type": 2,
      "isActive": 1,
      "time": "2026-07-23T08:35:15.556Z",
      "isDefault": 0,
      "remark": "speed:177ms",
      "tags": [],
      "priority": 0,
      "proxyMode": "none",
      "customProxy": ""
    },
    {
      "id": "499a564e-4ef8-40f2-8d44-66a582518577",
      "key": "最大点播",
      "name": "最大点播",
      "api": "http://zuidazy.me/api.php/provide/vod",
      "type": 2,
      "isActive": 1,
      "time": "2026-07-23T08:35:15.556Z",
      "isDefault": 0,
      "remark": "speed:177ms",
      "tags": [],
      "priority": 0,
      "proxyMode": "none",
      "customProxy": ""
    },
    {
      "id": "3be530e6-7d4a-4586-954d-8b30ead89c97",
      "key": "虎牙资源",
      "name": "虎牙资源",
      "api": "https://www.huyaapi.com/api.php/provide/vod",
      "type": 2,
      "isActive": 1,
      "time": "2026-07-23T08:35:15.556Z",
      "isDefault": 0,
      "remark": "speed:186ms",
      "tags": [],
      "priority": 0,
      "proxyMode": "none",
      "customProxy": ""
    },
    {
      "id": "494c5a2a-c25f-485c-8b4a-a44a5f12283e",
      "key": "天涯海角",
      "name": "天涯海角",
      "api": "https://tyyszyapi.com/api.php/provide/vod",
      "type": 2,
      "isActive": 1,
      "time": "2026-07-23T08:35:15.556Z",
      "isDefault": 0,
      "remark": "speed:216ms",
      "tags": [],
      "priority": 0,
      "proxyMode": "none",
      "customProxy": ""
    },
    {
      "id": "8575a13d-16e8-4267-92ac-6b6a401c8ba9",
      "key": "新浪资源",
      "name": "新浪资源",
      "api": "http://api.xinlangapi.com/xinlangapi.php/provide/vod",
      "type": 2,
      "isActive": 1,
      "time": "2026-07-23T08:35:15.556Z",
      "isDefault": 0,
      "remark": "speed:219ms",
      "tags": [],
      "priority": 0,
      "proxyMode": "none",
      "customProxy": ""
    },
    {
      "id": "846a6a1c-624c-4a9d-a270-ea40f939994a",
      "key": "樱花资源",
      "name": "樱花资源",
      "api": "https://m3u8.apiyhzy.com/api.php/provide/vod",
      "type": 2,
      "isActive": 1,
      "time": "2026-07-23T08:35:15.556Z",
      "isDefault": 0,
      "remark": "speed:223ms",
      "tags": [],
      "priority": 0,
      "proxyMode": "none",
      "customProxy": ""
    },
    {
      "id": "008ca216-1741-458b-bb25-2b7bc1a94f00",
      "key": "暴风资源",
      "name": "暴风资源",
      "api": "https://bfzyapi.com/api.php/provide/vod",
      "type": 2,
      "isActive": 1,
      "time": "2026-07-23T08:35:15.556Z",
      "isDefault": 0,
      "remark": "speed:224ms",
      "tags": [],
      "priority": 0,
      "proxyMode": "none",
      "customProxy": ""
    },
    {
      "id": "c0101b00-47f8-4344-a6ab-4c8187683c51",
      "key": "天涯资源",
      "name": "天涯资源",
      "api": "https://tyyszy.com/api.php/provide/vod",
      "type": 2,
      "isActive": 1,
      "time": "2026-07-23T08:35:15.556Z",
      "isDefault": 0,
      "remark": "speed:226ms",
      "tags": [],
      "priority": 0,
      "proxyMode": "none",
      "customProxy": ""
    },
    {
      "id": "00770ffc-e70d-4ef8-832f-0d999fa446bd",
      "key": "无尽ME",
      "name": "无尽ME",
      "api": "https://api.wujinapi.me/api.php/provide/vod",
      "type": 2,
      "isActive": 1,
      "time": "2026-07-23T08:35:15.556Z",
      "isDefault": 0,
      "remark": "speed:231ms",
      "tags": [],
      "priority": 0,
      "proxyMode": "none",
      "customProxy": ""
    },
    {
      "id": "2c1cb9f4-7935-4004-8185-081543b14718",
      "key": "牛牛点播",
      "name": "牛牛点播",
      "api": "https://api.niuniuzy.me/api.php/provide/vod",
      "type": 2,
      "isActive": 1,
      "time": "2026-07-23T08:35:15.556Z",
      "isDefault": 0,
      "remark": "speed:253ms",
      "tags": [],
      "priority": 0,
      "proxyMode": "none",
      "customProxy": ""
    },
    {
      "id": "cb162ff1-07f0-48d9-8fa1-3d55fa559abb",
      "key": "无尽CC",
      "name": "无尽CC",
      "api": "https://api.wujinapi.cc/api.php/provide/vod",
      "type": 2,
      "isActive": 1,
      "time": "2026-07-23T08:35:15.556Z",
      "isDefault": 0,
      "remark": "speed:270ms",
      "tags": [],
      "priority": 0,
      "proxyMode": "none",
      "customProxy": ""
    },
    {
      "id": "95cc7744-0cbe-45db-9862-7fae1509cefa",
      "key": "无尽资源",
      "name": "无尽资源",
      "api": "https://api.wujinapi.com/api.php/provide/vod",
      "type": 2,
      "isActive": 1,
      "time": "2026-07-23T08:35:15.556Z",
      "isDefault": 0,
      "remark": "speed:279ms",
      "tags": [],
      "priority": 0,
      "proxyMode": "none",
      "customProxy": ""
    },
    {
      "id": "215c061b-acca-4edd-b784-fa68ea99e98a",
      "key": "玉兔",
      "name": "玉兔",
      "api": "https://yutuzy10.com/api.php/provide/vod",
      "type": 2,
      "isActive": 1,
      "time": "2026-07-23T08:35:15.556Z",
      "isDefault": 0,
      "remark": "speed:284ms",
      "tags": [],
      "priority": 0,
      "proxyMode": "none",
      "customProxy": ""
    },
    {
      "id": "30dbfa48-8d05-4c44-8374-06744ae6f3a9",
      "key": "閃電资源",
      "name": "閃電资源",
      "api": "https://sdzyapi.com/api.php/provide/vod",
      "type": 2,
      "isActive": 1,
      "time": "2026-07-23T08:35:15.556Z",
      "isDefault": 0,
      "remark": "speed:288ms",
      "tags": [],
      "priority": 0,
      "proxyMode": "none",
      "customProxy": ""
    },
    {
      "id": "9473230b-5b48-4c34-8fae-647d26900021",
      "key": "乐子资源",
      "name": "乐子资源",
      "api": "https://cj.lziapi.com/api.php/provide/vod",
      "type": 2,
      "isActive": 1,
      "time": "2026-07-23T08:35:15.556Z",
      "isDefault": 0,
      "remark": "speed:302ms",
      "tags": [],
      "priority": 0,
      "proxyMode": "none",
      "customProxy": ""
    },
    {
      "id": "a32c3152-e8a5-47ae-a0d1-4edb7d57b481",
      "key": "索尼-闪电",
      "name": "索尼-闪电",
      "api": "https://xsd.sdzyapi.com/api.php/provide/vod",
      "type": 2,
      "isActive": 1,
      "time": "2026-07-23T08:35:15.556Z",
      "isDefault": 0,
      "remark": "speed:312ms",
      "tags": [],
      "priority": 0,
      "proxyMode": "none",
      "customProxy": ""
    },
    {
      "id": "006a58a5-a1c6-477b-9625-509e4e579d84",
      "key": "黄AV资源站",
      "name": "黄AV资源站",
      "api": "https://www.pgxdy.com/api/json.php",
      "type": 2,
      "isActive": 1,
      "time": "2026-07-23T08:35:15.556Z",
      "isDefault": 0,
      "remark": "speed:312ms",
      "tags": [],
      "priority": 0,
      "proxyMode": "none",
      "customProxy": ""
    },
    {
      "id": "401893a7-fa9c-4029-9ae2-458a5e091750",
      "key": "lsb",
      "name": "lsb",
      "api": "https://apilsbzy1.com/api.php/provide/vod",
      "type": 2,
      "isActive": 1,
      "time": "2026-07-23T08:35:15.556Z",
      "isDefault": 0,
      "remark": "speed:318ms",
      "tags": [],
      "priority": 0,
      "proxyMode": "none",
      "customProxy": ""
    },
    {
      "id": "f0ea24ef-b4b4-4601-b97b-3bb7396fe599",
      "key": "红牛资源3",
      "name": "红牛资源3",
      "api": "https://www.hongniuzy3.com/api.php/provide/vod",
      "type": 2,
      "isActive": 1,
      "time": "2026-07-23T08:35:15.556Z",
      "isDefault": 0,
      "remark": "speed:374ms",
      "tags": [],
      "priority": 0,
      "proxyMode": "none",
      "customProxy": ""
    },
    {
      "id": "6f1fd54e-0d1f-4644-8874-f10bc74a2976",
      "key": "黄色仓库",
      "name": "黄色仓库",
      "api": "https://hsckzy.vip/api.php/provide/vod",
      "type": 2,
      "isActive": 1,
      "time": "2026-07-23T08:35:15.556Z",
      "isDefault": 0,
      "remark": "speed:374ms",
      "tags": [],
      "priority": 0,
      "proxyMode": "none",
      "customProxy": ""
    },
    {
      "id": "37cedc71-0e32-4823-96ea-4e06d44ec040",
      "key": "红牛资源",
      "name": "红牛资源",
      "api": "https://www.hongniuzy2.com/api.php/provide/vod",
      "type": 2,
      "isActive": 1,
      "time": "2026-07-23T08:35:15.556Z",
      "isDefault": 0,
      "remark": "speed:414ms",
      "tags": [],
      "priority": 0,
      "proxyMode": "none",
      "customProxy": ""
    },
    {
      "id": "f4b4962b-05f8-4d4f-b1b8-c07fe29311b0",
      "key": "优酷资源",
      "name": "优酷资源",
      "api": "https://api.ukuapi.com/api.php/provide/vod",
      "type": 2,
      "isActive": 1,
      "time": "2026-07-23T08:35:15.556Z",
      "isDefault": 0,
      "remark": "speed:436ms",
      "tags": [],
      "priority": 0,
      "proxyMode": "none",
      "customProxy": ""
    },
    {
      "id": "f82f0c55-48a0-4417-b1d5-8d32fac0e24b",
      "key": "海豚资源",
      "name": "海豚资源",
      "api": "https://hhzyapi.com/api.php/provide/vod",
      "type": 2,
      "isActive": 1,
      "time": "2026-07-23T08:35:15.556Z",
      "isDefault": 0,
      "remark": "speed:440ms",
      "tags": [],
      "priority": 0,
      "proxyMode": "none",
      "customProxy": ""
    },
    {
      "id": "67be3c01-0696-401a-9793-cc2516188d6c",
      "key": "香奶儿资源站",
      "name": "香奶儿资源站",
      "api": "https://www.gdlsp.com/api/json.php",
      "type": 2,
      "isActive": 1,
      "time": "2026-07-23T08:35:15.556Z",
      "isDefault": 0,
      "remark": "speed:440ms",
      "tags": [],
      "priority": 0,
      "proxyMode": "none",
      "customProxy": ""
    },
    {
      "id": "52c531ea-091f-4277-96db-8820f9f426e9",
      "key": "乐播资源",
      "name": "乐播资源",
      "api": "https://lbapi9.com/api.php/provide/vod",
      "type": 2,
      "isActive": 1,
      "time": "2026-07-23T08:35:15.556Z",
      "isDefault": 0,
      "remark": "speed:442ms",
      "tags": [],
      "priority": 0,
      "proxyMode": "none",
      "customProxy": ""
    },
    {
      "id": "aaab8a02-9440-4807-b849-f9c0a6170656",
      "key": "iKun资源",
      "name": "iKun资源",
      "api": "https://ikunzyapi.com/api.php/provide/vod",
      "type": 2,
      "isActive": 1,
      "time": "2026-07-23T08:35:15.556Z",
      "isDefault": 0,
      "remark": "speed:444ms",
      "tags": [],
      "priority": 0,
      "proxyMode": "none",
      "customProxy": ""
    },
    {
      "id": "91dae9e5-3d79-4e43-88d7-64ee8de23711",
      "key": "淫水机资源站",
      "name": "淫水机资源站",
      "api": "https://www.xrbsp.com/api/json.php",
      "type": 2,
      "isActive": 1,
      "time": "2026-07-23T08:35:15.556Z",
      "isDefault": 0,
      "remark": "speed:468ms",
      "tags": [],
      "priority": 0,
      "proxyMode": "none",
      "customProxy": ""
    },
    {
      "id": "84f93a95-86b2-4753-8a3d-d327aee10a57",
      "key": "🪔聚合┃短剧",
      "name": "🪔聚合┃短剧",
      "api": "https://16409.kstore.vip/js/%E8%81%9A%E5%90%88%E7%9F%AD%E5%89%A7.js",
      "type": 2,
      "isActive": 1,
      "time": "2026-07-23T08:35:15.556Z",
      "isDefault": 0,
      "remark": "speed:476ms",
      "tags": [],
      "priority": 0,
      "proxyMode": "none",
      "customProxy": ""
    },
    {
      "id": "d822e698-7e38-4201-80d5-92118421cfad",
      "key": "🧲磁力在线┃原盘",
      "name": "🧲磁力在线┃原盘",
      "api": "https://16409.kstore.vip/js/dyg.json",
      "type": 2,
      "isActive": 1,
      "time": "2026-07-23T08:35:15.556Z",
      "isDefault": 0,
      "remark": "speed:525ms",
      "tags": [],
      "priority": 0,
      "proxyMode": "none",
      "customProxy": ""
    },
    {
      "id": "b6eb9771-d0c4-47c7-830b-1737410aea7c",
      "key": "旺旺资源",
      "name": "旺旺资源",
      "api": "https://wwzy.tv/api.php/provide/vod",
      "type": 2,
      "isActive": 1,
      "time": "2026-07-23T08:35:15.556Z",
      "isDefault": 0,
      "remark": "speed:529ms",
      "tags": [],
      "priority": 0,
      "proxyMode": "none",
      "customProxy": ""
    },
    {
      "id": "2fa64800-ae60-4789-a406-9fad1eb8ab29",
      "key": "番号资源",
      "name": "番号资源",
      "api": "http://fhapi9.com/api.php/provide/vod",
      "type": 2,
      "isActive": 1,
      "time": "2026-07-23T08:35:15.556Z",
      "isDefault": 0,
      "remark": "speed:554ms",
      "tags": [],
      "priority": 0,
      "proxyMode": "none",
      "customProxy": ""
    },
    {
      "id": "d02edcc0-bce7-49e6-8ae5-3b3edc97766d",
      "key": "美少女资源站",
      "name": "美少女资源站",
      "api": "https://www.msnii.com/api/json.php",
      "type": 2,
      "isActive": 1,
      "time": "2026-07-23T08:35:15.556Z",
      "isDefault": 0,
      "remark": "speed:556ms",
      "tags": [],
      "priority": 0,
      "proxyMode": "none",
      "customProxy": ""
    },
    {
      "id": "df3a8aff-f980-4bab-bddc-b660e029b738",
      "key": "豆瓣资源",
      "name": "豆瓣资源",
      "api": "https://dbzy.tv/api.php/provide/vod",
      "type": 2,
      "isActive": 1,
      "time": "2026-07-23T08:35:15.556Z",
      "isDefault": 0,
      "remark": "speed:579ms",
      "tags": [],
      "priority": 0,
      "proxyMode": "none",
      "customProxy": ""
    },
    {
      "id": "e40bc007-b824-418a-989d-cd35754d1502",
      "key": "非凡资源",
      "name": "非凡资源",
      "api": "http://ffzy5.tv/api.php/provide/vod",
      "type": 2,
      "isActive": 1,
      "time": "2026-07-23T08:35:15.556Z",
      "isDefault": 0,
      "remark": "speed:603ms",
      "tags": [],
      "priority": 0,
      "proxyMode": "none",
      "customProxy": ""
    },
    {
      "id": "6ca34255-d724-466a-849e-d161f027b857",
      "key": "旺旺API",
      "name": "旺旺API",
      "api": "https://api.wwzy.tv/api.php/provide/vod",
      "type": 2,
      "isActive": 1,
      "time": "2026-07-23T08:35:15.556Z",
      "isDefault": 0,
      "remark": "speed:619ms",
      "tags": [],
      "priority": 0,
      "proxyMode": "none",
      "customProxy": ""
    },
    {
      "id": "d8419955-84ca-4829-aa2c-56f5ccffa6b6",
      "key": "非凡线路1",
      "name": "非凡线路1",
      "api": "http://ffzy1.tv/api.php/provide/vod",
      "type": 2,
      "isActive": 1,
      "time": "2026-07-23T08:35:15.556Z",
      "isDefault": 0,
      "remark": "speed:624ms",
      "tags": [],
      "priority": 0,
      "proxyMode": "none",
      "customProxy": ""
    },
    {
      "id": "3857de58-1191-4e01-ac7a-c8d416813225",
      "key": "细胞采集",
      "name": "细胞采集",
      "api": "https://www.xxibaozyw.com/api.php/provide/vod",
      "type": 2,
      "isActive": 1,
      "time": "2026-07-23T08:35:15.556Z",
      "isDefault": 0,
      "remark": "speed:642ms",
      "tags": [],
      "priority": 0,
      "proxyMode": "none",
      "customProxy": ""
    },
    {
      "id": "ff51c841-4f56-44a3-a516-4a04cb566a22",
      "key": "卧龙采集",
      "name": "卧龙采集",
      "api": "https://collect.wolongzyw.com/api.php/provide/vod",
      "type": 2,
      "isActive": 1,
      "time": "2026-07-23T08:35:15.556Z",
      "isDefault": 0,
      "remark": "speed:688ms",
      "tags": [],
      "priority": 0,
      "proxyMode": "none",
      "customProxy": ""
    },
    {
      "id": "cb10f5c8-9065-48d3-b0f7-57b8043b8cfa",
      "key": "精品资源",
      "name": "精品资源",
      "api": "https://www.jingpinx.com/api.php/provide/vod",
      "type": 2,
      "isActive": 1,
      "time": "2026-07-23T08:35:15.556Z",
      "isDefault": 0,
      "remark": "speed:715ms",
      "tags": [],
      "priority": 0,
      "proxyMode": "none",
      "customProxy": ""
    },
    {
      "id": "9cacd16c-6080-4458-85b7-6a814bc9192d",
      "key": "卧龙资源",
      "name": "卧龙资源",
      "api": "https://wolongzyw.com/api.php/provide/vod",
      "type": 2,
      "isActive": 1,
      "time": "2026-07-23T08:35:15.556Z",
      "isDefault": 0,
      "remark": "speed:723ms",
      "tags": [],
      "priority": 0,
      "proxyMode": "none",
      "customProxy": ""
    },
    {
      "id": "67115a50-7dd0-4b2d-8f30-44347dedfd40",
      "key": "茅台资源",
      "name": "茅台资源",
      "api": "https://caiji.maotaizy.cc/api.php/provide/vod",
      "type": 2,
      "isActive": 1,
      "time": "2026-07-23T08:35:15.556Z",
      "isDefault": 0,
      "remark": "speed:814ms",
      "tags": [],
      "priority": 0,
      "proxyMode": "none",
      "customProxy": ""
    },
    {
      "id": "d698132d-0775-4af3-b136-6b3bad7da006",
      "key": "白嫖资源站",
      "name": "白嫖资源站",
      "api": "https://www.kxgav.com/api/json.php",
      "type": 2,
      "isActive": 1,
      "time": "2026-07-23T08:35:15.556Z",
      "isDefault": 0,
      "remark": "speed:834ms",
      "tags": [],
      "priority": 0,
      "proxyMode": "none",
      "customProxy": ""
    },
    {
      "id": "977bb5d8-0476-4317-9296-82d99f2b9d61",
      "key": "鲸鱼资源",
      "name": "鲸鱼资源",
      "api": "https://jyzyapi.com/provide/vod",
      "type": 2,
      "isActive": 1,
      "time": "2026-07-23T08:35:15.556Z",
      "isDefault": 0,
      "remark": "speed:875ms",
      "tags": [],
      "priority": 0,
      "proxyMode": "none",
      "customProxy": ""
    },
    {
      "id": "5946db6c-443f-42a3-8dbe-1dfbd4c6e088",
      "key": "后台发送接口2字获取最新",
      "name": "后台发送接口2字获取最新",
      "api": "https://mk1080.top/get.txt",
      "type": 2,
      "isActive": 1,
      "time": "2026-07-23T08:35:15.556Z",
      "isDefault": 0,
      "remark": "speed:878ms",
      "tags": [],
      "priority": 0,
      "proxyMode": "none",
      "customProxy": ""
    },
    {
      "id": "f685c80c-1fdd-422f-9d25-b6f3f161d9d5",
      "key": "奥斯卡资源",
      "name": "奥斯卡资源",
      "api": "https://aosikazy.com/api.php/provide/vod",
      "type": 2,
      "isActive": 1,
      "time": "2026-07-23T08:35:15.556Z",
      "isDefault": 0,
      "remark": "speed:894ms",
      "tags": [],
      "priority": 0,
      "proxyMode": "none",
      "customProxy": ""
    },
    {
      "id": "fc1ce822-86c0-43eb-a42b-e06c728212fd",
      "key": "速博资源",
      "name": "速博资源",
      "api": "https://subocaiji.com/api.php/provide/vod",
      "type": 2,
      "isActive": 1,
      "time": "2026-07-23T08:35:15.556Z",
      "isDefault": 0,
      "remark": "speed:948ms",
      "tags": [],
      "priority": 0,
      "proxyMode": "none",
      "customProxy": ""
    },
    {
      "id": "b5d369e3-09de-4c72-b8c1-b667f122ec4a",
      "key": "电影天堂",
      "name": "电影天堂",
      "api": "http://caiji.dyttzyapi.com/api.php/provide/vod",
      "type": 2,
      "isActive": 1,
      "time": "2026-07-23T08:35:15.556Z",
      "isDefault": 0,
      "remark": "speed:1021ms",
      "tags": [],
      "priority": 0,
      "proxyMode": "none",
      "customProxy": ""
    },
    {
      "id": "ef71fa77-abe2-43b1-bff6-948f76567619",
      "key": "非凡采集HTTPS",
      "name": "非凡采集HTTPS",
      "api": "https://cj.ffzyapi.com/api.php/provide/vod",
      "type": 2,
      "isActive": 1,
      "time": "2026-07-23T08:35:15.556Z",
      "isDefault": 0,
      "remark": "speed:1081ms",
      "tags": [],
      "priority": 0,
      "proxyMode": "none",
      "customProxy": ""
    },
    {
      "id": "84746467-798e-4c91-a42c-4cb96b17d5e1",
      "key": "非凡采集",
      "name": "非凡采集",
      "api": "http://cj.ffzyapi.com/api.php/provide/vod",
      "type": 2,
      "isActive": 1,
      "time": "2026-07-23T08:35:15.556Z",
      "isDefault": 0,
      "remark": "speed:1099ms",
      "tags": [],
      "priority": 0,
      "proxyMode": "none",
      "customProxy": ""
    },
    {
      "id": "be3a2c07-7a91-437b-911d-557e58d22bb3",
      "key": "魔都动漫",
      "name": "魔都动漫",
      "api": "https://caiji.moduapi.cc/api.php/provide/vod",
      "type": 2,
      "isActive": 1,
      "time": "2026-07-23T08:35:15.556Z",
      "isDefault": 0,
      "remark": "speed:1104ms",
      "tags": [],
      "priority": 0,
      "proxyMode": "none",
      "customProxy": ""
    },
    {
      "id": "789b8a91-2b08-49e6-beca-a5c3f7849935",
      "key": "奶香香",
      "name": "奶香香",
      "api": "https://Naixxzy.com/api.php/provide/vod",
      "type": 2,
      "isActive": 1,
      "time": "2026-07-23T08:35:15.556Z",
      "isDefault": 0,
      "remark": "speed:1226ms",
      "tags": [],
      "priority": 0,
      "proxyMode": "none",
      "customProxy": ""
    },
    {
      "id": "3b37683d-e4bc-4259-b275-e1f6010aadaf",
      "key": "魔都资源",
      "name": "魔都资源",
      "api": "https://www.mdzyapi.com/api.php/provide/vod",
      "type": 2,
      "isActive": 1,
      "time": "2026-07-23T08:35:15.556Z",
      "isDefault": 0,
      "remark": "speed:1278ms",
      "tags": [],
      "priority": 0,
      "proxyMode": "none",
      "customProxy": ""
    },
    {
      "id": "219c6fbf-2b5b-4f13-b200-5f5715956882",
      "key": "91麻豆",
      "name": "91麻豆",
      "api": "https://91md.me/api.php/provide/vod",
      "type": 2,
      "isActive": 1,
      "time": "2026-07-23T08:35:15.556Z",
      "isDefault": 0,
      "remark": "speed:1285ms",
      "tags": [],
      "priority": 0,
      "proxyMode": "none",
      "customProxy": ""
    },
    {
      "id": "aa7893a9-90cb-4289-b8af-e9fdb8346332",
      "key": "360资源",
      "name": "360资源",
      "api": "https://360zy.com/api.php/provide/vod",
      "type": 2,
      "isActive": 1,
      "time": "2026-07-23T08:35:15.556Z",
      "isDefault": 0,
      "remark": "speed:1317ms",
      "tags": [],
      "priority": 0,
      "proxyMode": "none",
      "customProxy": ""
    },
    {
      "id": "1f1d1b0e-a40d-44dd-9142-aadf9365600b",
      "key": "光速资源",
      "name": "光速资源",
      "api": "https://api.guangsuapi.com/api.php/provide/vod",
      "type": 2,
      "isActive": 1,
      "time": "2026-07-23T08:35:15.556Z",
      "isDefault": 0,
      "remark": "speed:1345ms",
      "tags": [],
      "priority": 0,
      "proxyMode": "none",
      "customProxy": ""
    },
    {
      "id": "ea4b9a0b-2847-4c01-960d-0858b4b9f3ae",
      "key": "极速资源",
      "name": "极速资源",
      "api": "https://jszyapi.com/api.php/provide/vod",
      "type": 2,
      "isActive": 1,
      "time": "2026-07-23T08:35:15.556Z",
      "isDefault": 0,
      "remark": "speed:1469ms",
      "tags": [],
      "priority": 0,
      "proxyMode": "none",
      "customProxy": ""
    },
    {
      "id": "3f6c4c38-cdee-486a-a2b2-4cbbea36ca50",
      "key": "如意资源",
      "name": "如意资源",
      "api": "https://cj.rycjapi.com/api.php/provide/vod",
      "type": 2,
      "isActive": 1,
      "time": "2026-07-23T08:35:15.556Z",
      "isDefault": 0,
      "remark": "speed:1695ms",
      "tags": [],
      "priority": 0,
      "proxyMode": "none",
      "customProxy": ""
    },
    {
      "id": "5b6d8095-f6ce-49e0-a770-3235b86f3601",
      "key": "森林资源",
      "name": "森林资源",
      "api": "https://slapibf.com/api.php/provide/vod",
      "type": 2,
      "isActive": 1,
      "time": "2026-07-23T08:35:15.556Z",
      "isDefault": 0,
      "remark": "speed:1712ms",
      "tags": [],
      "priority": 0,
      "proxyMode": "none",
      "customProxy": ""
    },
    {
      "id": "a3e871de-b934-4747-8ea4-f8f859b7bdcb",
      "key": "1080JSON",
      "name": "1080JSON",
      "api": "https://api.1080zyku.com/inc/apijson.php",
      "type": 2,
      "isActive": 1,
      "time": "2026-07-23T08:35:15.556Z",
      "isDefault": 0,
      "remark": "speed:1859ms",
      "tags": [],
      "priority": 0,
      "proxyMode": "none",
      "customProxy": ""
    },
    {
      "id": "d56f5173-dbb2-4d69-82d5-5500abef2427",
      "key": "非凡API",
      "name": "非凡API",
      "api": "https://api.ffzyapi.com/api.php/provide/vod",
      "type": 2,
      "isActive": 1,
      "time": "2026-07-23T08:35:15.556Z",
      "isDefault": 0,
      "remark": "speed:1916ms",
      "tags": [],
      "priority": 0,
      "proxyMode": "none",
      "customProxy": ""
    },
    {
      "id": "d6684824-a66a-4031-9bd9-eea469402926",
      "key": "魔都影视",
      "name": "魔都影视",
      "api": "https://www.moduzy.com/api.php/provide/vod",
      "type": 2,
      "isActive": 1,
      "time": "2026-07-23T08:35:15.556Z",
      "isDefault": 0,
      "remark": "speed:2029ms",
      "tags": [],
      "priority": 0,
      "proxyMode": "none",
      "customProxy": ""
    },
    {
      "id": "770ae1da-b684-4995-a6f5-bca0d4de5651",
      "key": "鲨鱼资源",
      "name": "鲨鱼资源",
      "api": "https://shayuapi.com/api.php/provide/vod",
      "type": 2,
      "isActive": 1,
      "time": "2026-07-23T08:35:15.556Z",
      "isDefault": 0,
      "remark": "speed:2846ms",
      "tags": [],
      "priority": 0,
      "proxyMode": "none",
      "customProxy": ""
    }
  ]
}